.gitignore
.pre-commit-config.yaml
.pylintrc
CITATION.cff
CONTRIBUTING.rst
README.rst
codemeta.json
download_test_data.sh
environment.yml
license.rst
setup.py
.github/pull_request_template.md
.github/workflows/CI.yml
.github/workflows/docs.yml
.github/workflows/pypi.yml
.github/workflows/dev/codemeta2citation.py
docs/Makefile
docs/cli.rst
docs/conf.py
docs/index.rst
docs/lstmcpipe_user_doc.md
docs/make.bat
docs/pipeline.rst
docs/produce_config_page.py
docs/productions.rst
docs/requirements.txt
docs/examples/configs_pointings.ipynb
lstmcpipe/__init__.py
lstmcpipe/_version.py
lstmcpipe/base_config_lstmcpipe.yaml
lstmcpipe/logging.py
lstmcpipe/lstmcpipe_start.py
lstmcpipe/utils.py
lstmcpipe/version.py
lstmcpipe.egg-info/PKG-INFO
lstmcpipe.egg-info/SOURCES.txt
lstmcpipe.egg-info/dependency_links.txt
lstmcpipe.egg-info/entry_points.txt
lstmcpipe.egg-info/requires.txt
lstmcpipe.egg-info/top_level.txt
lstmcpipe/_dev_version/_dev_version.py
lstmcpipe/benchmarks/__init__.py
lstmcpipe/benchmarks/irfs.py
lstmcpipe/config/__init__.py
lstmcpipe/config/dl1ab_tuning.py
lstmcpipe/config/paths_config.py
lstmcpipe/config/pipeline_config.py
lstmcpipe/config/tests/__init__.py
lstmcpipe/config/tests/test_paths_config.py
lstmcpipe/config/tests/test_pipeline_config.py
lstmcpipe/hiperta/__init__.py
lstmcpipe/hiperta/hiperta_r0_to_dl1lstchain.py
lstmcpipe/hiperta/reorganize_dl1hiperta300_to_dl1lstchain060.py
lstmcpipe/hiperta/reorganize_dl1hiperta_to_dl1lstchain.py
lstmcpipe/io/__init__.py
lstmcpipe/io/data_management.py
lstmcpipe/io/lstmcpipe_tree_path.py
lstmcpipe/io/tests/__init__.py
lstmcpipe/io/tests/test_data_management.py
lstmcpipe/io/tests/test_lstmcpipe_tree_path.py
lstmcpipe/plots/__init__.py
lstmcpipe/plots/images_debug.py
lstmcpipe/plots/plot_irfs.py
lstmcpipe/plots/plot_models_importance.py
lstmcpipe/plots/pointings.py
lstmcpipe/plots/tests/test_pointings.py
lstmcpipe/scripts/__init__.py
lstmcpipe/scripts/generate_nsb_levels_configs.py
lstmcpipe/scripts/generate_test_lapalma.py
lstmcpipe/scripts/lstmcpipe_generate_config.py
lstmcpipe/scripts/script_batch_filelist_cta.py
lstmcpipe/scripts/script_batch_filelist_lst.py
lstmcpipe/scripts/script_batch_filelist_lst_dl1ab.py
