Metadata-Version: 2.1
Name: lstmcpipe
Version: 0.11.1
Summary: Scripts to ease the reduction of MC data on the LST cluster at La Palma. With this package, the analysis/creation of R1/DL0/DL1/DL2/IRFs can be orchestrated.
Home-page: https://github.com/cta-observatory/lstmcpipe
Author: Thomas Vuillaume,Enrique Garcia,Lukas Nickel,Arnau Aguasca-Cabot,
Author-email: thomas.vuillaume@lapp.in2p3.fr
License: MIT
Classifier: Intended Audience :: Science/Research
Classifier: Programming Language :: Python :: 3
Classifier: Topic :: Scientific/Engineering :: Astronomy
Requires-Dist: lstchain>=0.9.0
Requires-Dist: numpy
Requires-Dist: astropy
Requires-Dist: ctaplot>=0.5
Requires-Dist: pyirf>=0.4
Requires-Dist: matplotlib
Requires-Dist: pytest
Requires-Dist: ruamel.yaml>=0.17
Requires-Dist: setuptools_scm<8.0
Requires-Dist: deepdiff
